preprocmachine/__init__.py
preprocmachine/automation.py
preprocmachine/preprocmachine.py
preprocmachine/algorithms/__init__.py
preprocmachine/algorithms/linear_regression.py
preprocmachine/preprocessing/__init__.py
preprocmachine/preprocessing/duplicate_detection.py
preprocmachine/preprocessing/feature_selection.py
preprocmachine/preprocessing/imputation.py
preprocmachine/preprocessing/normalization.py
preprocmachine/preprocessing/outlier_detection.py
preprocmachine/utils/__init__.py
preprocmachine/utils/data.py
preprocmachine/utils/greedy.py
preprocmachine-0.0.2.dist-info/LICENSE
preprocmachine-0.0.2.dist-info/METADATA
preprocmachine-0.0.2.dist-info/WHEEL
preprocmachine-0.0.2.dist-info/top_level.txt
preprocmachine-0.0.2.dist-info/RECORD
