Metadata-Version: 2.1
Name: preprocmachine
Version: 0.0.2
Summary: A tool to automate preprocessing phase.
Home-page: https://github.com/yashm28sjsu/preprocmachine
Author: William Su, Yash Modi, Niranjan Reddy Masapeta
Author-email: modiyash3393@gmail.com
License: MIT license
Keywords: preprocmachine
Platform: UNKNOWN
Classifier: Development Status :: 2 - Pre-Alpha
Classifier: Intended Audience :: Developers
Classifier: License :: OSI Approved :: MIT License
Classifier: Natural Language :: English
Classifier: Programming Language :: Python :: 3
Classifier: Programming Language :: Python :: 3.6
Classifier: Programming Language :: Python :: 3.7
Classifier: Programming Language :: Python :: 3.8
Requires-Python: >=3.6
License-File: LICENSE
Requires-Dist: numpy (==1.21.4)
Requires-Dist: pandas (==1.3.4)
Requires-Dist: scipy (==1.7.3)
Requires-Dist: scikit-learn (==1.0.1)
